cocomo/cocomo.py
cocomo/__init__.py
cocomo-0.3.1.dist-info/DESCRIPTION.rst
cocomo-0.3.1.dist-info/entry_points.txt
cocomo-0.3.1.dist-info/RECORD
cocomo-0.3.1.dist-info/WHEEL
cocomo-0.3.1.dist-info/top_level.txt
cocomo-0.3.1.dist-info/metadata.json
cocomo-0.3.1.dist-info/METADATA
